cloudcoil/models/knative_eventing/__init__.py
cloudcoil/models/knative_eventing/py.typed
cloudcoil/models/knative_eventing/eventing/__init__.py
cloudcoil/models/knative_eventing/eventing/v1.py
cloudcoil/models/knative_eventing/eventing/v1alpha1.py
cloudcoil/models/knative_eventing/eventing/v1beta1.py
cloudcoil/models/knative_eventing/eventing/v1beta2.py
cloudcoil/models/knative_eventing/eventing/v1beta3.py
cloudcoil/models/knative_eventing/flows/__init__.py
cloudcoil/models/knative_eventing/flows/v1.py
cloudcoil/models/knative_eventing/messaging/__init__.py
cloudcoil/models/knative_eventing/messaging/v1.py
cloudcoil/models/knative_eventing/sinks/__init__.py
cloudcoil/models/knative_eventing/sinks/v1alpha1.py
cloudcoil/models/knative_eventing/sources/__init__.py
cloudcoil/models/knative_eventing/sources/v1.py
cloudcoil/models/knative_eventing/sources/v1alpha1.py
cloudcoil/models/knative_eventing/sources/v1beta2.py
cloudcoil_models_knative_eventing-1.17.1.0.dist-info/METADATA
cloudcoil_models_knative_eventing-1.17.1.0.dist-info/WHEEL
cloudcoil_models_knative_eventing-1.17.1.0.dist-info/licenses/LICENSE
cloudcoil_models_knative_eventing-1.17.1.0.dist-info/RECORD
